lotto/__init__.py
lotto/admin.py
lotto/apps.py
lotto/forms.py
lotto/models.py
lotto/tests.py
lotto/urls.py
lotto/views.py
lotto/migrations/0001_initial.py
lotto/migrations/0002_auto_20180507_1634.py
lotto/migrations/__init__.py
lotto/static/lotto/style.css
lotto/templates/lotto/index.html
djangolotto-0.1.1.dist-info/LICENSE
djangolotto-0.1.1.dist-info/METADATA
djangolotto-0.1.1.dist-info/WHEEL
djangolotto-0.1.1.dist-info/top_level.txt
djangolotto-0.1.1.dist-info/RECORD
